wordwright/__init__.py
wordwright/count_keywords.py
wordwright/count_sentences.py
wordwright/language_detection.py
wordwright/preprocessing.py
wordwright/word_frequency.py
wordwright-3.0.1.dist-info/LICENSE
wordwright-3.0.1.dist-info/METADATA
wordwright-3.0.1.dist-info/WHEEL
wordwright-3.0.1.dist-info/RECORD
