Metadata-Version: 2.1
Name: wordwright
Version: 3.0.1
Summary: A package for text processing
License: MIT
Author: Group 4
Requires-Python: >=3.9
Classifier: License :: OSI Approved :: MIT License
Classifier: Programming Language :: Python :: 3
Classifier: Programming Language :: Python :: 3.9
Classifier: Programming Language :: Python :: 3.10
Classifier: Programming Language :: Python :: 3.11
Classifier: Programming Language :: Python :: 3.12
Requires-Dist: counter (>=1.0.0)
Requires-Dist: detect (>=2020.12.3)
Requires-Dist: langdetect (>=1.0.9,<2.0.0)
Requires-Dist: matplotlib (>=3.8.2)
Requires-Dist: nltk (>=3.8.1)
Requires-Dist: wordcloud (>=1.9.3)
